pyglview
